{
    "USERNAME": "ZANdewanai",
    "MC_AETHER": true,
    "WANDERER_NAME": "Wanderer",
    "GAME_RESOLUTION": 1080,
    "USE_GPU": true,
    "ADAPTED_NAMES_4P_COORD": [
        [
            2165,
            330,
            2362,
            401
        ],
        [
            2165,
            470,
            2362,
            542
        ],
        [
            2165,
            565,
            2360,
            640
        ],
        [
            2165,
            755,
            2362,
            828
        ]
    ],
    "ADAPTED_NUMBER_4P_COORD": [
        [
            2480,
            350,
            2510,
            380
        ],
        [
            2480,
            472,
            2510,
            502
        ],
        [
            2480,
            592,
            2510,
            622
        ],
        [
            2480,
            717,
            2510,
            747
        ]
    ],
    "ADAPTATION_ACTIVE": true,
    "ADAPTATION_HISTORY": [],
    "OCCUPIED_SLOTS": [
        null,
        null,
        2,
        3
    ]
}